Metadata-Version: 2.1
Name: picklerpc
Version: 0.1.0
Home-page: https://github.com/chenxinfeng4/picklerpc
Author: chenxf
Author-email: cxf529125853@163.com
Requires-Python: >=3.6
